hikumi_generator/__init__.py
hikumi_generator/docswriter.py
hikumi_generator/sourcebuilder.py
hikumi_generator/syncerrors.py
hikumi_generator/utils.py
hikumi_generator/generators/__init__.py
hikumi_generator/generators/docs.py
hikumi_generator/generators/errors.py
hikumi_generator/generators/tlobject.py
hikumi_generator/parsers/__init__.py
hikumi_generator/parsers/errors.py
hikumi_generator/parsers/methods.py
hikumi_generator/parsers/tlobject/__init__.py
hikumi_generator/parsers/tlobject/parser.py
hikumi_generator/parsers/tlobject/tlarg.py
hikumi_generator/parsers/tlobject/tlobject.py
hikumitl/__init__.py
hikumitl/custom.py
hikumitl/functions.py
hikumitl/helpers.py
hikumitl/hints.py
hikumitl/password.py
hikumitl/requestiter.py
hikumitl/sync.py
hikumitl/types.py
hikumitl/utils.py
hikumitl/version.py
hikumitl/_updates/__init__.py
hikumitl/_updates/entitycache.py
hikumitl/_updates/messagebox.py
hikumitl/_updates/session.py
hikumitl/client/__init__.py
hikumitl/client/account.py
hikumitl/client/auth.py
hikumitl/client/bots.py
hikumitl/client/buttons.py
hikumitl/client/chats.py
hikumitl/client/dialogs.py
hikumitl/client/downloads.py
hikumitl/client/messageparse.py
hikumitl/client/messages.py
hikumitl/client/telegrambaseclient.py
hikumitl/client/telegramclient.py
hikumitl/client/updates.py
hikumitl/client/uploads.py
hikumitl/client/users.py
hikumitl/crypto/__init__.py
hikumitl/crypto/aes.py
hikumitl/crypto/aesctr.py
hikumitl/crypto/authkey.py
hikumitl/crypto/cdndecrypter.py
hikumitl/crypto/factorization.py
hikumitl/crypto/libssl.py
hikumitl/crypto/rsa.py
hikumitl/errors/__init__.py
hikumitl/errors/common.py
hikumitl/errors/rpcbaseerrors.py
hikumitl/errors/rpcerrorlist.py
hikumitl/events/__init__.py
hikumitl/events/album.py
hikumitl/events/callbackquery.py
hikumitl/events/chataction.py
hikumitl/events/common.py
hikumitl/events/inlinequery.py
hikumitl/events/messagedeleted.py
hikumitl/events/messageedited.py
hikumitl/events/messageread.py
hikumitl/events/newmessage.py
hikumitl-1.40.3.dist-info/licenses/LICENSE
hikumitl-1.40.3.dist-info/METADATA
hikumitl-1.40.3.dist-info/WHEEL
hikumitl-1.40.3.dist-info/top_level.txt
hikumitl-1.40.3.dist-info/RECORD
