Metadata-Version: 2.4
Name: hikumitl
Version: 1.40.3
Summary: Full-featured Telegram client library for Python 3
Home-page: https://github.com/Plovchikdeval/hikumitl
Download-URL: https://github.com/Plovchikdeval/hikumitl/releases
Author: Pavel Nedelko
Author-email: dev3quest@gmail.com
License: MIT
Keywords: telegram api chat client library messaging mtproto
Classifier: Development Status :: 5 - Production/Stable
Classifier: Intended Audience :: Developers
Classifier: Topic :: Communications :: Chat
Classifier: License :: OSI Approved :: MIT License
Classifier: Programming Language :: Python :: 3
Classifier: Programming Language :: Python :: 3.5
Classifier: Programming Language :: Python :: 3.6
Classifier: Programming Language :: Python :: 3.7
Classifier: Programming Language :: Python :: 3.8
Requires-Python: >=3.5
License-File: LICENSE
Requires-Dist: pyaes
Requires-Dist: rsa==4.9
Requires-Dist: aiofile==3.8.1
Requires-Dist: gitpython==3.1.27
Requires-Dist: meval==2.5
Requires-Dist: aiohttp_jinja2==1.5
Requires-Dist: aiohttp==3.8.3
Requires-Dist: Jinja2==3.0.3
Requires-Dist: requests==2.27.1
Requires-Dist: aiogram==2.19
Requires-Dist: grapheme==0.6.0
Requires-Dist: emoji==2.1.0
Requires-Dist: werkzeug==2.2.2
Requires-Dist: psutil==5.9.4
Requires-Dist: tgcrypto==1.2.5
Requires-Dist: ruamel.yaml==0.17.21
Provides-Extra: cryptg
Requires-Dist: cryptg; extra == "cryptg"
Dynamic: author
Dynamic: author-email
Dynamic: classifier
Dynamic: description
Dynamic: download-url
Dynamic: home-page
Dynamic: keywords
Dynamic: license
Dynamic: license-file
Dynamic: provides-extra
Dynamic: requires-dist
Dynamic: requires-python
Dynamic: summary
